azure/eventhub/extensions/checkpointstoreblobaio/__init__.py
azure/eventhub/extensions/checkpointstoreblobaio/_blobstoragecsaio.py
azure/eventhub/extensions/checkpointstoreblobaio/_version.py
azure/eventhub/extensions/checkpointstoreblobaio/_vendor/__init__.py
azure/eventhub/extensions/checkpointstoreblobaio/_vendor/storage/__init__.py
azure/eventhub/extensions/checkpointstoreblobaio/_vendor/storage/blob/__init__.py
azure/eventhub/extensions/checkpointstoreblobaio/_vendor/storage/blob/_blob_client.py
azure/eventhub/extensions/checkpointstoreblobaio/_vendor/storage/blob/_blob_service_client.py
azure/eventhub/extensions/checkpointstoreblobaio/_vendor/storage/blob/_container_client.py
azure/eventhub/extensions/checkpointstoreblobaio/_vendor/storage/blob/_deserialize.py
azure/eventhub/extensions/checkpointstoreblobaio/_vendor/storage/blob/_download.py
azure/eventhub/extensions/checkpointstoreblobaio/_vendor/storage/blob/_lease.py
azure/eventhub/extensions/checkpointstoreblobaio/_vendor/storage/blob/_list_blobs_helper.py
azure/eventhub/extensions/checkpointstoreblobaio/_vendor/storage/blob/_models.py
azure/eventhub/extensions/checkpointstoreblobaio/_vendor/storage/blob/_quick_query_helper.py
azure/eventhub/extensions/checkpointstoreblobaio/_vendor/storage/blob/_serialize.py
azure/eventhub/extensions/checkpointstoreblobaio/_vendor/storage/blob/_shared_access_signature.py
azure/eventhub/extensions/checkpointstoreblobaio/_vendor/storage/blob/_upload_helpers.py
azure/eventhub/extensions/checkpointstoreblobaio/_vendor/storage/blob/_version.py
azure/eventhub/extensions/checkpointstoreblobaio/_vendor/storage/blob/_generated/__init__.py
azure/eventhub/extensions/checkpointstoreblobaio/_vendor/storage/blob/_generated/_azure_blob_storage.py
azure/eventhub/extensions/checkpointstoreblobaio/_vendor/storage/blob/_generated/_configuration.py
azure/eventhub/extensions/checkpointstoreblobaio/_vendor/storage/blob/_generated/aio/__init__.py
azure_eventhub_checkpointstoreblob_aio-1.1.4.dist-info/LICENSE
azure_eventhub_checkpointstoreblob_aio-1.1.4.dist-info/METADATA
azure_eventhub_checkpointstoreblob_aio-1.1.4.dist-info/WHEEL
azure_eventhub_checkpointstoreblob_aio-1.1.4.dist-info/top_level.txt
azure_eventhub_checkpointstoreblob_aio-1.1.4.dist-info/RECORD
