Metadata-Version: 2.1
Name: azure-eventhub-checkpointstoreblob-aio
Version: 1.1.4
Summary: Microsoft Azure Event Hubs checkpointer implementation with Blob Storage Client Library for Python
Home-page: https://github.com/Azure/azure-sdk-for-python/tree/master/sdk/eventhub/azure-eventhub-checkpointstoreblob-aio
Author: Microsoft Corporation
Author-email: azpysdkhelp@microsoft.com
License: MIT License
Platform: UNKNOWN
Classifier: Development Status :: 5 - Production/Stable
Classifier: Programming Language :: Python
Classifier: Programming Language :: Python :: 3
Classifier: Programming Language :: Python :: 3.6
Classifier: Programming Language :: Python :: 3.7
Classifier: Programming Language :: Python :: 3.8
Classifier: Programming Language :: Python :: 3.9
Classifier: License :: OSI Approved :: MIT License
Requires-Python: >=3.6
